{
  "$schema": "https://developer.microsoft.com/json-schemas/fabric/item/report/definition/bookmark/1.4.0/schema.json",
  "displayName": "Product Overview",
  "name": "5a8a8d3903c8e0a58043",
  "options": {
    "targetVisualNames": []
  },
  "explorationState": {
    "version": "1.3",
    "activeSection": "5ac6b0fd4dab9aee76a2",
    "sections": {
      "5ac6b0fd4dab9aee76a2": {
        "visualContainers": {
          "6d70f78c850843919011": {
            "filters": {
              "byExpr": [
                {
                  "name": "dcb39ca725316bda0834",
                  "type": "Advanced",
                  "expression": {
                    "Measure": {
                      "Expression": {
                        "SourceRef": {
                          "Entity": "olist_orders_dataset"
                        }
                      },
                      "Property": "InsightHint"
                    }
                  },
                  "howCreated": 0
                }
              ]
            },
            "singleVisual": {
              "visualType": "card",
              "objects": {}
            }
          },
          "416c5810aa008ca299bc": {
            "singleVisual": {
              "visualType": "shape",
              "objects": {}
            }
          },
          "d604196495ccd6dda5ae": {
            "singleVisual": {
              "visualType": "textbox",
              "objects": {}
            }
          },
          "8a2215c0302074e953c3": {
            "singleVisual": {
              "visualType": "actionButton",
              "objects": {}
            }
          },
          "7e563b0320714e1a9d29": {
            "singleVisual": {
              "visualType": "actionButton",
              "objects": {}
            }
          },
          "985ba1b6b5dec3a96d46": {
            "singleVisual": {
              "visualType": "actionButton",
              "objects": {}
            }
          },
          "1db3467a874e0e628bae": {
            "singleVisual": {
              "visualType": "actionButton",
              "objects": {}
            }
          },
          "1a37547700120c651c6d": {
            "singleVisual": {
              "visualType": "shape",
              "objects": {}
            }
          },
          "2ab060a716e9edd28478": {
            "filters": {
              "byName": {
                "ee92369842e183430466": {
                  "name": "ee92369842e183430466",
                  "type": "TopN",
                  "filter": {
                    "Version": 2,
                    "From": [
                      {
                        "Name": "subquery",
                        "Expression": {
                          "Subquery": {
                            "Query": {
                              "Version": 2,
                              "From": [
                                {
                                  "Name": "o",
                                  "Entity": "olist_products_dataset",
                                  "Type": 0
                                },
                                {
                                  "Name": "o1",
                                  "Entity": "olist_order_items_dataset",
                                  "Type": 0
                                }
                              ],
                              "Select": [
                                {
                                  "Column": {
                                    "Expression": {
                                      "SourceRef": {
                                        "Source": "o"
                                      }
                                    },
                                    "Property": "product_category_name"
                                  },
                                  "Name": "field"
                                }
                              ],
                              "OrderBy": [
                                {
                                  "Direction": 2,
                                  "Expression": {
                                    "Measure": {
                                      "Expression": {
                                        "SourceRef": {
                                          "Source": "o1"
                                        }
                                      },
                                      "Property": "Total Revenue"
                                    }
                                  }
                                }
                              ],
                              "Top": 5
                            }
                          }
                        },
                        "Type": 2
                      },
                      {
                        "Name": "o",
                        "Entity": "olist_products_dataset",
                        "Type": 0
                      }
                    ],
                    "Where": [
                      {
                        "Condition": {
                          "In": {
                            "Expressions": [
                              {
                                "Column": {
                                  "Expression": {
                                    "SourceRef": {
                                      "Source": "o"
                                    }
                                  },
                                  "Property": "product_category_name"
                                }
                              }
                            ],
                            "Table": {
                              "SourceRef": {
                                "Source": "subquery"
                              }
                            }
                          }
                        }
                      }
                    ]
                  },
                  "expression": {
                    "Column": {
                      "Expression": {
                        "SourceRef": {
                          "Entity": "olist_products_dataset"
                        }
                      },
                      "Property": "product_category_name"
                    }
                  },
                  "howCreated": 0
                }
              },
              "byExpr": [
                {
                  "name": "70fafff585c79229abfa",
                  "type": "Advanced",
                  "expression": {
                    "Measure": {
                      "Expression": {
                        "SourceRef": {
                          "Entity": "olist_order_items_dataset"
                        }
                      },
                      "Property": "Total Revenue"
                    }
                  },
                  "howCreated": 0
                }
              ]
            },
            "singleVisual": {
              "visualType": "clusteredBarChart",
              "objects": {},
              "orderBy": [
                {
                  "Direction": 2,
                  "Expression": {
                    "Measure": {
                      "Expression": {
                        "SourceRef": {
                          "Entity": "olist_order_items_dataset"
                        }
                      },
                      "Property": "Total Revenue"
                    }
                  }
                }
              ],
              "activeProjections": {
                "Category": [
                  {
                    "Column": {
                      "Expression": {
                        "SourceRef": {
                          "Entity": "olist_products_dataset"
                        }
                      },
                      "Property": "product_category_name"
                    }
                  }
                ]
              }
            }
          },
          "2bc64120875c77836a0c": {
            "filters": {
              "byExpr": [
                {
                  "name": "40798623b72cb321f28f",
                  "type": "TopN",
                  "filter": {
                    "Version": 2,
                    "From": [
                      {
                        "Name": "subquery",
                        "Expression": {
                          "Subquery": {
                            "Query": {
                              "Version": 2,
                              "From": [
                                {
                                  "Name": "o",
                                  "Entity": "olist_products_dataset",
                                  "Type": 0
                                },
                                {
                                  "Name": "o1",
                                  "Entity": "olist_order_items_dataset",
                                  "Type": 0
                                }
                              ],
                              "Select": [
                                {
                                  "Column": {
                                    "Expression": {
                                      "SourceRef": {
                                        "Source": "o"
                                      }
                                    },
                                    "Property": "product_category_name"
                                  },
                                  "Name": "field"
                                }
                              ],
                              "OrderBy": [
                                {
                                  "Direction": 2,
                                  "Expression": {
                                    "Measure": {
                                      "Expression": {
                                        "SourceRef": {
                                          "Source": "o1"
                                        }
                                      },
                                      "Property": "Total Revenue"
                                    }
                                  }
                                }
                              ],
                              "Top": 5
                            }
                          }
                        },
                        "Type": 2
                      },
                      {
                        "Name": "o",
                        "Entity": "olist_products_dataset",
                        "Type": 0
                      }
                    ],
                    "Where": [
                      {
                        "Condition": {
                          "In": {
                            "Expressions": [
                              {
                                "Column": {
                                  "Expression": {
                                    "SourceRef": {
                                      "Source": "o"
                                    }
                                  },
                                  "Property": "product_category_name"
                                }
                              }
                            ],
                            "Table": {
                              "SourceRef": {
                                "Source": "subquery"
                              }
                            }
                          }
                        }
                      }
                    ]
                  },
                  "expression": {
                    "Column": {
                      "Expression": {
                        "SourceRef": {
                          "Entity": "olist_products_dataset"
                        }
                      },
                      "Property": "product_category_name"
                    }
                  },
                  "howCreated": 0
                },
                {
                  "name": "889a428518a13df76c5a",
                  "type": "Advanced",
                  "expression": {
                    "Measure": {
                      "Expression": {
                        "SourceRef": {
                          "Entity": "olist_order_items_dataset"
                        }
                      },
                      "Property": "Total Orders"
                    }
                  },
                  "howCreated": 0
                }
              ]
            },
            "singleVisual": {
              "visualType": "clusteredBarChart",
              "objects": {},
              "orderBy": [
                {
                  "Direction": 2,
                  "Expression": {
                    "Measure": {
                      "Expression": {
                        "SourceRef": {
                          "Entity": "olist_order_items_dataset"
                        }
                      },
                      "Property": "Total Orders"
                    }
                  }
                }
              ],
              "activeProjections": {
                "Category": [
                  {
                    "Column": {
                      "Expression": {
                        "SourceRef": {
                          "Entity": "olist_products_dataset"
                        }
                      },
                      "Property": "product_category_name"
                    }
                  }
                ]
              }
            }
          },
          "e2091af20e7db6487690": {
            "filters": {
              "byExpr": [
                {
                  "name": "22388c8b38701d0a1613",
                  "type": "TopN",
                  "filter": {
                    "Version": 2,
                    "From": [
                      {
                        "Name": "subquery",
                        "Expression": {
                          "Subquery": {
                            "Query": {
                              "Version": 2,
                              "From": [
                                {
                                  "Name": "o1",
                                  "Entity": "olist_products_dataset",
                                  "Type": 0
                                },
                                {
                                  "Name": "o",
                                  "Entity": "olist_reviews_dataset",
                                  "Type": 0
                                }
                              ],
                              "Select": [
                                {
                                  "Column": {
                                    "Expression": {
                                      "SourceRef": {
                                        "Source": "o1"
                                      }
                                    },
                                    "Property": "product_category_name"
                                  },
                                  "Name": "field"
                                }
                              ],
                              "OrderBy": [
                                {
                                  "Direction": 1,
                                  "Expression": {
                                    "Aggregation": {
                                      "Expression": {
                                        "Column": {
                                          "Expression": {
                                            "SourceRef": {
                                              "Source": "o"
                                            }
                                          },
                                          "Property": "review_score"
                                        }
                                      },
                                      "Function": 0
                                    }
                                  }
                                }
                              ],
                              "Top": 5
                            }
                          }
                        },
                        "Type": 2
                      },
                      {
                        "Name": "o1",
                        "Entity": "olist_products_dataset",
                        "Type": 0
                      }
                    ],
                    "Where": [
                      {
                        "Condition": {
                          "In": {
                            "Expressions": [
                              {
                                "Column": {
                                  "Expression": {
                                    "SourceRef": {
                                      "Source": "o1"
                                    }
                                  },
                                  "Property": "product_category_name"
                                }
                              }
                            ],
                            "Table": {
                              "SourceRef": {
                                "Source": "subquery"
                              }
                            }
                          }
                        }
                      }
                    ]
                  },
                  "expression": {
                    "Column": {
                      "Expression": {
                        "SourceRef": {
                          "Entity": "olist_products_dataset"
                        }
                      },
                      "Property": "product_category_name"
                    }
                  },
                  "howCreated": 0
                },
                {
                  "name": "d2661f3c61adab83cd8e",
                  "type": "Advanced",
                  "expression": {
                    "Aggregation": {
                      "Expression": {
                        "Column": {
                          "Expression": {
                            "SourceRef": {
                              "Entity": "olist_reviews_dataset"
                            }
                          },
                          "Property": "review_score"
                        }
                      },
                      "Function": 1
                    }
                  },
                  "howCreated": 0
                }
              ]
            },
            "singleVisual": {
              "visualType": "clusteredColumnChart",
              "objects": {},
              "orderBy": [
                {
                  "Direction": 2,
                  "Expression": {
                    "Aggregation": {
                      "Expression": {
                        "Column": {
                          "Expression": {
                            "SourceRef": {
                              "Entity": "olist_reviews_dataset"
                            }
                          },
                          "Property": "review_score"
                        }
                      },
                      "Function": 1
                    }
                  }
                }
              ],
              "activeProjections": {
                "Category": [
                  {
                    "Column": {
                      "Expression": {
                        "SourceRef": {
                          "Entity": "olist_products_dataset"
                        }
                      },
                      "Property": "product_category_name"
                    }
                  }
                ]
              }
            }
          },
          "21fd6cfc98aac96a02c3": {
            "filters": {
              "byName": {
                "ee92369842e183430466": {
                  "name": "ee92369842e183430466",
                  "type": "TopN",
                  "filter": {
                    "Version": 2,
                    "From": [
                      {
                        "Name": "subquery",
                        "Expression": {
                          "Subquery": {
                            "Query": {
                              "Version": 2,
                              "From": [
                                {
                                  "Name": "o",
                                  "Entity": "olist_products_dataset",
                                  "Type": 0
                                },
                                {
                                  "Name": "o1",
                                  "Entity": "olist_order_items_dataset",
                                  "Type": 0
                                }
                              ],
                              "Select": [
                                {
                                  "Column": {
                                    "Expression": {
                                      "SourceRef": {
                                        "Source": "o"
                                      }
                                    },
                                    "Property": "product_category_name"
                                  },
                                  "Name": "field"
                                }
                              ],
                              "OrderBy": [
                                {
                                  "Direction": 2,
                                  "Expression": {
                                    "Measure": {
                                      "Expression": {
                                        "SourceRef": {
                                          "Source": "o1"
                                        }
                                      },
                                      "Property": "Total Revenue"
                                    }
                                  }
                                }
                              ],
                              "Top": 5
                            }
                          }
                        },
                        "Type": 2
                      },
                      {
                        "Name": "o",
                        "Entity": "olist_products_dataset",
                        "Type": 0
                      }
                    ],
                    "Where": [
                      {
                        "Condition": {
                          "In": {
                            "Expressions": [
                              {
                                "Column": {
                                  "Expression": {
                                    "SourceRef": {
                                      "Source": "o"
                                    }
                                  },
                                  "Property": "product_category_name"
                                }
                              }
                            ],
                            "Table": {
                              "SourceRef": {
                                "Source": "subquery"
                              }
                            }
                          }
                        }
                      }
                    ]
                  },
                  "expression": {
                    "Column": {
                      "Expression": {
                        "SourceRef": {
                          "Entity": "olist_products_dataset"
                        }
                      },
                      "Property": "product_category_name"
                    }
                  },
                  "howCreated": 0
                }
              },
              "byExpr": [
                {
                  "name": "1edeb7e6eb25677e65d9",
                  "type": "Advanced",
                  "expression": {
                    "Measure": {
                      "Expression": {
                        "SourceRef": {
                          "Entity": "olist_order_items_dataset"
                        }
                      },
                      "Property": "Total Revenue"
                    }
                  },
                  "howCreated": 0
                }
              ]
            },
            "singleVisual": {
              "visualType": "treemap",
              "objects": {},
              "orderBy": [
                {
                  "Direction": 2,
                  "Expression": {
                    "Measure": {
                      "Expression": {
                        "SourceRef": {
                          "Entity": "olist_order_items_dataset"
                        }
                      },
                      "Property": "Total Revenue"
                    }
                  }
                }
              ],
              "activeProjections": {
                "Group": [
                  {
                    "Column": {
                      "Expression": {
                        "SourceRef": {
                          "Entity": "olist_products_dataset"
                        }
                      },
                      "Property": "product_category_name"
                    }
                  }
                ]
              }
            }
          },
          "7f3057f51bd990a0adee": {
            "filters": {
              "byExpr": [
                {
                  "name": "003fa3cb777b6c7827e6",
                  "type": "Advanced",
                  "expression": {
                    "Measure": {
                      "Expression": {
                        "SourceRef": {
                          "Entity": "olist_products_dataset"
                        }
                      },
                      "Property": "Product_category_count"
                    }
                  },
                  "howCreated": 0
                }
              ]
            },
            "singleVisual": {
              "visualType": "card",
              "objects": {},
              "orderBy": [
                {
                  "Direction": 2,
                  "Expression": {
                    "Measure": {
                      "Expression": {
                        "SourceRef": {
                          "Entity": "olist_products_dataset"
                        }
                      },
                      "Property": "Product_category_count"
                    }
                  }
                }
              ]
            }
          },
          "70960a72216ce7a131d2": {
            "singleVisual": {
              "visualType": "textbox",
              "objects": {}
            }
          },
          "b1e85578003d43300b41": {
            "singleVisual": {
              "visualType": "textbox",
              "objects": {}
            }
          },
          "7f829ffd1d93727d5200": {
            "singleVisual": {
              "visualType": "textbox",
              "objects": {}
            }
          },
          "008df7e081d8c89d2396": {
            "filters": {
              "byName": {
                "2570c210ec30d50970c4": {
                  "name": "2570c210ec30d50970c4",
                  "type": "Categorical",
                  "filter": {
                    "Version": 2,
                    "From": [
                      {
                        "Name": "l",
                        "Entity": "LocalDateTable_c54e583f-5196-4a67-b863-4e64ce630ae5",
                        "Type": 0
                      }
                    ],
                    "Where": [
                      {
                        "Condition": {
                          "Not": {
                            "Expression": {
                              "In": {
                                "Expressions": [
                                  {
                                    "Column": {
                                      "Expression": {
                                        "SourceRef": {
                                          "Source": "l"
                                        }
                                      },
                                      "Property": "Month"
                                    }
                                  }
                                ],
                                "Values": [
                                  [
                                    {
                                      "Literal": {
                                        "Value": "null"
                                      }
                                    }
                                  ]
                                ]
                              }
                            }
                          }
                        }
                      }
                    ]
                  },
                  "expression": {
                    "HierarchyLevel": {
                      "Expression": {
                        "Hierarchy": {
                          "Expression": {
                            "PropertyVariationSource": {
                              "Expression": {
                                "SourceRef": {
                                  "Entity": "Dates"
                                }
                              },
                              "Name": "Variation",
                              "Property": "Date"
                            }
                          },
                          "Hierarchy": "Date Hierarchy"
                        }
                      },
                      "Level": "Month"
                    }
                  },
                  "howCreated": 0,
                  "cachedDisplayNames": [
                    {
                      "id": {
                        "scopeId": {
                          "Comparison": {
                            "ComparisonKind": 0,
                            "Left": {
                              "Column": {
                                "Expression": {
                                  "SourceRef": {
                                    "Entity": "LocalDateTable_c54e583f-5196-4a67-b863-4e64ce630ae5"
                                  }
                                },
                                "Property": "Month"
                              }
                            },
                            "Right": {
                              "Literal": {
                                "Value": "null"
                              }
                            }
                          }
                        }
                      },
                      "displayName": "(Blank)"
                    }
                  ]
                }
              }
            },
            "singleVisual": {
              "visualType": "slicer",
              "objects": {
                "merge": {
                  "data": [
                    {
                      "properties": {
                        "endDate": {
                          "expr": {
                            "Literal": {
                              "Value": "datetime'2025-03-31T00:00:00'"
                            }
                          }
                        },
                        "mode": {
                          "expr": {
                            "Literal": {
                              "Value": "'Basic'"
                            }
                          }
                        }
                      }
                    }
                  ]
                }
              },
              "activeProjections": {
                "Values": [
                  {
                    "HierarchyLevel": {
                      "Expression": {
                        "Hierarchy": {
                          "Expression": {
                            "PropertyVariationSource": {
                              "Expression": {
                                "SourceRef": {
                                  "Entity": "Dates"
                                }
                              },
                              "Name": "Variation",
                              "Property": "Date"
                            }
                          },
                          "Hierarchy": "Date Hierarchy"
                        }
                      },
                      "Level": "Month"
                    }
                  }
                ]
              }
            }
          },
          "854ac077638627d0766b": {
            "filters": {
              "byName": {
                "fb2427105601006aa70b": {
                  "name": "fb2427105601006aa70b",
                  "type": "Categorical",
                  "expression": {
                    "HierarchyLevel": {
                      "Expression": {
                        "Hierarchy": {
                          "Expression": {
                            "PropertyVariationSource": {
                              "Expression": {
                                "SourceRef": {
                                  "Entity": "Dates"
                                }
                              },
                              "Name": "Variation",
                              "Property": "Date"
                            }
                          },
                          "Hierarchy": "Date Hierarchy"
                        }
                      },
                      "Level": "Month"
                    }
                  },
                  "howCreated": 1
                },
                "5f740b9410658997343d": {
                  "name": "5f740b9410658997343d",
                  "type": "Categorical",
                  "filter": {
                    "Version": 2,
                    "From": [
                      {
                        "Name": "l",
                        "Entity": "LocalDateTable_c54e583f-5196-4a67-b863-4e64ce630ae5",
                        "Type": 0
                      }
                    ],
                    "Where": [
                      {
                        "Condition": {
                          "Not": {
                            "Expression": {
                              "In": {
                                "Expressions": [
                                  {
                                    "Column": {
                                      "Expression": {
                                        "SourceRef": {
                                          "Source": "l"
                                        }
                                      },
                                      "Property": "Year"
                                    }
                                  }
                                ],
                                "Values": [
                                  [
                                    {
                                      "Literal": {
                                        "Value": "null"
                                      }
                                    }
                                  ]
                                ]
                              }
                            }
                          }
                        }
                      }
                    ]
                  },
                  "expression": {
                    "HierarchyLevel": {
                      "Expression": {
                        "Hierarchy": {
                          "Expression": {
                            "PropertyVariationSource": {
                              "Expression": {
                                "SourceRef": {
                                  "Entity": "Dates"
                                }
                              },
                              "Name": "Variation",
                              "Property": "Date"
                            }
                          },
                          "Hierarchy": "Date Hierarchy"
                        }
                      },
                      "Level": "Year"
                    }
                  },
                  "howCreated": 0,
                  "cachedDisplayNames": [
                    {
                      "id": {
                        "scopeId": {
                          "Comparison": {
                            "ComparisonKind": 0,
                            "Left": {
                              "Column": {
                                "Expression": {
                                  "SourceRef": {
                                    "Entity": "LocalDateTable_c54e583f-5196-4a67-b863-4e64ce630ae5"
                                  }
                                },
                                "Property": "Year"
                              }
                            },
                            "Right": {
                              "Literal": {
                                "Value": "null"
                              }
                            }
                          }
                        }
                      },
                      "displayName": "(Blank)"
                    }
                  ]
                }
              }
            },
            "singleVisual": {
              "visualType": "slicer",
              "objects": {
                "merge": {
                  "data": [
                    {
                      "properties": {
                        "mode": {
                          "expr": {
                            "Literal": {
                              "Value": "'Basic'"
                            }
                          }
                        }
                      }
                    }
                  ]
                }
              },
              "orderBy": [
                {
                  "Direction": 1,
                  "Expression": {
                    "HierarchyLevel": {
                      "Expression": {
                        "Hierarchy": {
                          "Expression": {
                            "PropertyVariationSource": {
                              "Expression": {
                                "SourceRef": {
                                  "Entity": "Dates"
                                }
                              },
                              "Name": "Variation",
                              "Property": "Date"
                            }
                          },
                          "Hierarchy": "Date Hierarchy"
                        }
                      },
                      "Level": "Year"
                    }
                  }
                }
              ],
              "activeProjections": {
                "Values": [
                  {
                    "HierarchyLevel": {
                      "Expression": {
                        "Hierarchy": {
                          "Expression": {
                            "PropertyVariationSource": {
                              "Expression": {
                                "SourceRef": {
                                  "Entity": "Dates"
                                }
                              },
                              "Name": "Variation",
                              "Property": "Date"
                            }
                          },
                          "Hierarchy": "Date Hierarchy"
                        }
                      },
                      "Level": "Year"
                    }
                  }
                ]
              }
            }
          },
          "cabc75970d0cda97e5b4": {
            "filters": {
              "byName": {
                "1e0ac8e7d87e8b08b424": {
                  "name": "1e0ac8e7d87e8b08b424",
                  "type": "Categorical",
                  "filter": {
                    "Version": 2,
                    "From": [
                      {
                        "Name": "l",
                        "Entity": "LocalDateTable_c54e583f-5196-4a67-b863-4e64ce630ae5",
                        "Type": 0
                      }
                    ],
                    "Where": [
                      {
                        "Condition": {
                          "Not": {
                            "Expression": {
                              "In": {
                                "Expressions": [
                                  {
                                    "Column": {
                                      "Expression": {
                                        "SourceRef": {
                                          "Source": "l"
                                        }
                                      },
                                      "Property": "Quarter"
                                    }
                                  }
                                ],
                                "Values": [
                                  [
                                    {
                                      "Literal": {
                                        "Value": "null"
                                      }
                                    }
                                  ]
                                ]
                              }
                            }
                          }
                        }
                      }
                    ]
                  },
                  "expression": {
                    "HierarchyLevel": {
                      "Expression": {
                        "Hierarchy": {
                          "Expression": {
                            "PropertyVariationSource": {
                              "Expression": {
                                "SourceRef": {
                                  "Entity": "Dates"
                                }
                              },
                              "Name": "Variation",
                              "Property": "Date"
                            }
                          },
                          "Hierarchy": "Date Hierarchy"
                        }
                      },
                      "Level": "Quarter"
                    }
                  },
                  "howCreated": 0,
                  "cachedDisplayNames": [
                    {
                      "id": {
                        "scopeId": {
                          "Comparison": {
                            "ComparisonKind": 0,
                            "Left": {
                              "Column": {
                                "Expression": {
                                  "SourceRef": {
                                    "Entity": "LocalDateTable_c54e583f-5196-4a67-b863-4e64ce630ae5"
                                  }
                                },
                                "Property": "Quarter"
                              }
                            },
                            "Right": {
                              "Literal": {
                                "Value": "null"
                              }
                            }
                          }
                        }
                      },
                      "displayName": "(Blank)"
                    }
                  ]
                }
              }
            },
            "singleVisual": {
              "visualType": "slicer",
              "objects": {
                "merge": {
                  "data": [
                    {
                      "properties": {
                        "endDate": {
                          "expr": {
                            "Literal": {
                              "Value": "datetime'2025-03-31T00:00:00'"
                            }
                          }
                        },
                        "mode": {
                          "expr": {
                            "Literal": {
                              "Value": "'Basic'"
                            }
                          }
                        }
                      }
                    }
                  ]
                }
              },
              "activeProjections": {
                "Values": [
                  {
                    "HierarchyLevel": {
                      "Expression": {
                        "Hierarchy": {
                          "Expression": {
                            "PropertyVariationSource": {
                              "Expression": {
                                "SourceRef": {
                                  "Entity": "Dates"
                                }
                              },
                              "Name": "Variation",
                              "Property": "Date"
                            }
                          },
                          "Hierarchy": "Date Hierarchy"
                        }
                      },
                      "Level": "Quarter"
                    }
                  }
                ]
              }
            }
          },
          "cbe2ff616b2e1a65d285": {
            "singleVisual": {
              "visualType": "shape",
              "objects": {}
            }
          },
          "151a00cb851a1b2a3b96": {
            "filters": {
              "byExpr": [
                {
                  "name": "f21705dd03f03ae090b5",
                  "type": "Advanced",
                  "expression": {
                    "Aggregation": {
                      "Expression": {
                        "Column": {
                          "Expression": {
                            "SourceRef": {
                              "Entity": "olist_reviews_dataset"
                            }
                          },
                          "Property": "review_score"
                        }
                      },
                      "Function": 1
                    }
                  },
                  "howCreated": 0
                }
              ]
            },
            "singleVisual": {
              "visualType": "card",
              "objects": {},
              "orderBy": [
                {
                  "Direction": 2,
                  "Expression": {
                    "Aggregation": {
                      "Expression": {
                        "Column": {
                          "Expression": {
                            "SourceRef": {
                              "Entity": "olist_reviews_dataset"
                            }
                          },
                          "Property": "review_score"
                        }
                      },
                      "Function": 1
                    }
                  }
                }
              ]
            }
          },
          "2f10aa6a4b5df900b2c9": {
            "filters": {
              "byName": {
                "05498f38a74141236b7c": {
                  "name": "05498f38a74141236b7c",
                  "type": "Categorical",
                  "filter": {
                    "Version": 2,
                    "From": [
                      {
                        "Name": "l",
                        "Entity": "location",
                        "Type": 0
                      }
                    ],
                    "Where": [
                      {
                        "Condition": {
                          "Not": {
                            "Expression": {
                              "In": {
                                "Expressions": [
                                  {
                                    "Column": {
                                      "Expression": {
                                        "SourceRef": {
                                          "Source": "l"
                                        }
                                      },
                                      "Property": "full_state"
                                    }
                                  }
                                ],
                                "Values": [
                                  [
                                    {
                                      "Literal": {
                                        "Value": "null"
                                      }
                                    }
                                  ]
                                ]
                              }
                            }
                          }
                        }
                      }
                    ]
                  },
                  "expression": {
                    "Column": {
                      "Expression": {
                        "SourceRef": {
                          "Entity": "location"
                        }
                      },
                      "Property": "full_state"
                    }
                  },
                  "howCreated": 0
                }
              }
            },
            "singleVisual": {
              "visualType": "slicer",
              "objects": {
                "merge": {
                  "data": [
                    {
                      "properties": {
                        "mode": {
                          "expr": {
                            "Literal": {
                              "Value": "'Dropdown'"
                            }
                          }
                        }
                      }
                    }
                  ]
                }
              },
              "activeProjections": {
                "Values": [
                  {
                    "Column": {
                      "Expression": {
                        "SourceRef": {
                          "Entity": "location"
                        }
                      },
                      "Property": "full_state"
                    }
                  }
                ]
              }
            }
          },
          "effd08350cd108c2a42a": {
            "filters": {
              "byExpr": [
                {
                  "name": "1ef7c0075b95131fe748",
                  "type": "Categorical",
                  "expression": {
                    "Column": {
                      "Expression": {
                        "SourceRef": {
                          "Entity": "olist_products_dataset"
                        }
                      },
                      "Property": "product_category_name"
                    }
                  },
                  "howCreated": 0
                }
              ]
            },
            "singleVisual": {
              "visualType": "slicer",
              "objects": {
                "merge": {
                  "data": [
                    {
                      "properties": {
                        "mode": {
                          "expr": {
                            "Literal": {
                              "Value": "'Dropdown'"
                            }
                          }
                        }
                      }
                    }
                  ]
                }
              },
              "activeProjections": {
                "Values": [
                  {
                    "Column": {
                      "Expression": {
                        "SourceRef": {
                          "Entity": "olist_products_dataset"
                        }
                      },
                      "Property": "product_category_name"
                    }
                  }
                ]
              }
            }
          },
          "8a9fbf0f118359c2c9a9": {
            "filters": {
              "byExpr": [
                {
                  "name": "dc7dabdbad0aed3d9759",
                  "type": "Categorical",
                  "expression": {
                    "Column": {
                      "Expression": {
                        "SourceRef": {
                          "Entity": "olist_geolocation_dataset"
                        }
                      },
                      "Property": "geolocation_city"
                    }
                  },
                  "howCreated": 0
                }
              ]
            },
            "singleVisual": {
              "visualType": "slicer",
              "objects": {
                "merge": {
                  "data": [
                    {
                      "properties": {
                        "mode": {
                          "expr": {
                            "Literal": {
                              "Value": "'Dropdown'"
                            }
                          }
                        }
                      }
                    }
                  ]
                }
              },
              "activeProjections": {
                "Values": [
                  {
                    "Column": {
                      "Expression": {
                        "SourceRef": {
                          "Entity": "olist_geolocation_dataset"
                        }
                      },
                      "Property": "geolocation_city"
                    }
                  }
                ]
              }
            }
          }
        }
      }
    },
    "objects": {
      "merge": {
        "outspacePane": [
          {
            "properties": {
              "expanded": {
                "expr": {
                  "Literal": {
                    "Value": "false"
                  }
                }
              }
            }
          }
        ]
      }
    }
  }
}